MANIFEST.in
README.txt
setup.py
docs/HISTORY.txt
docs/INSTALL.txt
docs/LICENSE.GPL
docs/LICENSE.txt
quintagroup/__init__.py
quintagroup.theme.techlight.egg-info/PKG-INFO
quintagroup.theme.techlight.egg-info/SOURCES.txt
quintagroup.theme.techlight.egg-info/dependency_links.txt
quintagroup.theme.techlight.egg-info/entry_points.txt
quintagroup.theme.techlight.egg-info/namespace_packages.txt
quintagroup.theme.techlight.egg-info/not-zip-safe
quintagroup.theme.techlight.egg-info/requires.txt
quintagroup.theme.techlight.egg-info/top_level.txt
quintagroup/theme/__init__.py
quintagroup/theme/techlight/README.txt
quintagroup/theme/techlight/__init__.py
quintagroup/theme/techlight/configure.zcml
quintagroup/theme/techlight/profiles/default/metadata.xml
quintagroup/theme/techlight/profiles/default/theme.xml
quintagroup/theme/techlight/profiles/default/tinymce.xml
quintagroup/theme/techlight/static/extra.html
quintagroup/theme/techlight/static/index.html
quintagroup/theme/techlight/static/manifest.cfg
quintagroup/theme/techlight/static/rules.xml
quintagroup/theme/techlight/static/css/IEFixes.css
quintagroup/theme/techlight/static/css/techlight.css
quintagroup/theme/techlight/static/images/album.png
quintagroup/theme/techlight/static/images/favicon.ico
quintagroup/theme/techlight/static/images/icons-sprite.png
quintagroup/theme/techlight/static/images/logoTechlight.gif
quintagroup/theme/techlight/static/images/pb_close.png
quintagroup/theme/techlight/static/images/techlight_sprite.png